drfapigenerator/__init__.py
drfapigenerator/admin.py
drfapigenerator/apps.py
drfapigenerator/models.py
drfapigenerator/tests.py
drfapigenerator/views.py
drfapigenerator/management/__init__.py
drfapigenerator/management/commands/__init__.py
drfapigenerator/management/commands/cleanapi.py
drfapigenerator/management/commands/makeapi.py
drfapigenerator/management/commands/restoreapi.py
drfapigenerator/management/commands/data/__init__.py
drfapigenerator/management/commands/data/urls_data.py
drfapigenerator/management/commands/data/routers/__init__.py
drfapigenerator/management/commands/data/routers/backup.txt
drfapigenerator/management/commands/data/routers/import.txt
drfapigenerator/management/commands/data/routers/routers.txt
drfapigenerator/management/commands/data/serializers/__init__.py
drfapigenerator/management/commands/data/serializers/serializers.txt
drfapigenerator/management/commands/data/utilities/__init__.py
drfapigenerator/management/commands/data/utilities/importbase.txt
drfapigenerator/management/commands/data/utilities/pagination.txt
drfapigenerator/management/commands/data/utilities/permissions.txt
drfapigenerator/management/commands/data/viewsets/__init__.py
drfapigenerator/management/commands/data/viewsets/viewsets.txt
drfapigenerator/management/commands/utilities/__init__.py
drfapigenerator/management/commands/utilities/app_management.py
drfapigenerator/management/commands/utilities/auto_api.py
drfapigenerator/management/commands/utilities/base_tasks.py
drfapigenerator/management/commands/utilities/supports/__init__.py
drfapigenerator/management/commands/utilities/supports/base_exists.py
drfapigenerator/management/commands/utilities/supports/helper/__init__.py
drfapigenerator/management/commands/utilities/supports/helper/helper.py
drfapigenerator/migrations/__init__.py
drfapigenerator-4.5.0.dist-info/METADATA
drfapigenerator-4.5.0.dist-info/WHEEL
drfapigenerator-4.5.0.dist-info/top_level.txt
drfapigenerator-4.5.0.dist-info/RECORD
